{
  "main": {
    "id": "1bff7eee2809abd7",
    "type": "split",
    "children": [
      {
        "id": "77cf4cb32c4f27a4",
        "type": "tabs",
        "children": [
          {
            "id": "60c6b86bf6d224da",
            "type": "leaf",
            "state": {
              "type": "markdown",
              "state": {
                "file": "FrameWorks/Vue/Transitions & Animations.md",
                "mode": "source",
                "source": false
              }
            }
          },
          {
            "id": "e92210adcf99929d",
            "type": "leaf",
            "state": {
              "type": "markdown",
              "state": {
                "file": "FrameWorks/Spring/Annotations/Annotations.md",
                "mode": "source",
                "source": false
              }
            }
          }
        ],
        "currentTab": 1
      }
    ],
    "direction": "vertical"
  },
  "left": {
    "id": "2b00aa544f64cb6c",
    "type": "split",
    "children": [
      {
        "id": "5bde26942bed3ad9",
        "type": "tabs",
        "children": [
          {
            "id": "2ce1a846a1685820",
            "type": "leaf",
            "state": {
              "type": "file-explorer",
              "state": {
                "sortOrder": "alphabetical"
              }
            }
          },
          {
            "id": "1f8860850a8475f5",
            "type": "leaf",
            "state": {
              "type": "search",
              "state": {
                "query": "",
                "matchingCase": false,
                "explainSearch": false,
                "collapseAll": false,
                "extraContext": false,
                "sortOrder": "alphabetical"
              }
            }
          },
          {
            "id": "c5f1e2c05e4a3f5c",
            "type": "leaf",
            "state": {
              "type": "bookmarks",
              "state": {}
            }
          }
        ]
      }
    ],
    "direction": "horizontal",
    "width": 200
  },
  "right": {
    "id": "f5151c0da72edc1c",
    "type": "split",
    "children": [
      {
        "id": "7b201216a9f66b74",
        "type": "tabs",
        "children": [
          {
            "id": "f45c8ecf3a5f1faa",
            "type": "leaf",
            "state": {
              "type": "backlink",
              "state": {
                "file": "FrameWorks/Spring/Annotations/Annotations.md",
                "collapseAll": false,
                "extraContext": false,
                "sortOrder": "alphabetical",
                "showSearch": false,
                "searchQuery": "",
                "backlinkCollapsed": false,
                "unlinkedCollapsed": true
              }
            }
          },
          {
            "id": "fc469dfb3e98dd32",
            "type": "leaf",
            "state": {
              "type": "outgoing-link",
              "state": {
                "file": "FrameWorks/Spring/Annotations/Annotations.md",
                "linksCollapsed": false,
                "unlinkedCollapsed": true
              }
            }
          },
          {
            "id": "1059f11db8c8ea19",
            "type": "leaf",
            "state": {
              "type": "tag",
              "state": {
                "sortOrder": "frequency",
                "useHierarchy": true
              }
            }
          },
          {
            "id": "2d48c83eecf2f279",
            "type": "leaf",
            "state": {
              "type": "outline",
              "state": {
                "file": "FrameWorks/Spring/Annotations/Annotations.md"
              }
            }
          }
        ]
      }
    ],
    "direction": "horizontal",
    "width": 300,
    "collapsed": true
  },
  "left-ribbon": {
    "hiddenItems": {
      "switcher:퀵 스위처 열기": false,
      "graph:그래프 뷰 열기": false,
      "canvas:새 캔버스 만들기": false,
      "daily-notes:오늘의 데일리 노트 열기": false,
      "templates:템플릿 삽입": false,
      "command-palette:명령어 팔레트 열기": false
    }
  },
  "active": "2ce1a846a1685820",
  "lastOpenFiles": [
    "Message-Broker/RabbitMQ",
    "Message-Broker",
    "FrameWorks/Spring/Convert/RTSP to HLS (FFmpeg).md",
    "FrameWorks/Spring/Convert/CSV Parser.md",
    "FrameWorks/Spring/Convert/Json.md",
    "FrameWorks/Spring/Convert",
    "Database/Dump.md",
    "CS/Web Application & Network.md",
    "CS/Race Condition.md",
    "CS/Proxy & Loadbalancer & Was & VPC.md",
    "CS/HTTP.md",
    "CS/Cookie & Session.md",
    "CS/Context Switching.md",
    "CS/공식.md",
    "FrameWorks/Spring/Spring Batch.md",
    "FrameWorks/Spring/Undertow.md",
    "FrameWorks/Spring/MQTT.md",
    "FrameWorks/Spring/채팅방구현/2. Kafka 설치 & MongoDB & Stomp 설정.md",
    "FrameWorks/Spring/채팅방구현/1. 기술스택 선정.md",
    "FrameWorks/Vue/Transitions & Animations.md",
    "AWS/Cloud Front.md",
    "Data Handling/풀이/Programmers/정렬/가장 큰 수.md",
    "Data Handling/풀이/Programmers/정렬/K번째수.md",
    "Data Handling/풀이/Programmers/정렬/H-Index.md",
    "Data Handling/풀이/Programmers/완전탐색/최소직사각형.md",
    "Data Handling/풀이/Programmers/완전탐색/모의고사.md",
    "Data Handling/풀이/Programmers/Stack & Queue/프린터.md",
    "Data Handling/풀이/Programmers/Stack & Queue/올바른괄호.md",
    "Data Handling/풀이/Programmers/정렬",
    "Data Handling/풀이/Programmers/완전탐색",
    "Data Handling/풀이/Programmers/Stack & Queue",
    "Data Handling/풀이/Programmers/Hash",
    "Data Handling/풀이/Programmers/DFS & BFS",
    "Data Handling/풀이/Programmers",
    "Data Handling/풀이/CodeUp",
    "Data Handling/풀이/Baek Joon",
    "Pasted image 20230805163438.png"
  ]
}